{
    "name": "Jill Carlson",
    "age": 92,
    "address": {
        "street": "Robinson Well",
        "city": "Lake Melissamouth",
        "state": "Kansas",
        "zip": "10567"
    },
    "contact": {
        "phone": "+1-571-940-7480x52868",
        "servicePhone": "800629454"
    },
    "birthday": "1933-16-11",
    "ip": "40.142.221.165",
    "foo": "bar",
    "profile": {
        "about": "Then back protect major big chance point. Address floor learn important. Build less capital forget work research per.",
        "bio": "Hard fear soldier perhaps. Particularly institution poor system stand somebody its where. Theory moment social pick success ready.\nForward behavior around remain. Realize air short door seat."
    },
    "currency": [
        "IRR",
        "Iranian rial"
    ]
}